parolo/__init__.py
parolo/_core.py
parolo/prompt.py
parolo/tenants.py
parolo-0.2.1.dist-info/METADATA
parolo-0.2.1.dist-info/WHEEL
parolo-0.2.1.dist-info/top_level.txt
parolo-0.2.1.dist-info/RECORD
