Metadata-Version: 2.4
Name: parolo
Version: 0.2.1
Summary: A version-controlled prompt system for LLM workflows.
Author-email: Matthias Rebel <matthias.rebel@gmail.com>
Requires-Python: >=3.11
Requires-Dist: Jinja2<4,>=3.1
Provides-Extra: dev
Requires-Dist: pytest>=8.4.1; extra == "dev"
Requires-Dist: build; extra == "dev"
Requires-Dist: ruff; extra == "dev"
